update_version/__init__.py
update_version/__init__.pyi
update_version/__main__.py
update_version/py.typed
update_version/types.py
update_version/types.pyi
update_version/update.py
update_version/update.pyi
update_version/util.py
update_version/util.pyi
update_version/version.py
update_version/version.pyi
update_version/args/__init__.py
update_version/args/__init__.pyi
update_version/args/parsing.py
update_version/args/parsing.pyi
update_version-0.1.5.dist-info/licenses/LICENSE
update_version-0.1.5.dist-info/METADATA
update_version-0.1.5.dist-info/WHEEL
update_version-0.1.5.dist-info/entry_points.txt
update_version-0.1.5.dist-info/top_level.txt
update_version-0.1.5.dist-info/RECORD
